compas_timber/__init__.py
compas_timber/__version__.py
compas_timber/connections/__init__.py
compas_timber/connections/analyzers.py
compas_timber/connections/ball_node.py
compas_timber/connections/butt_joint.py
compas_timber/connections/joint.py
compas_timber/connections/joint_candidate.py
compas_timber/connections/l_butt.py
compas_timber/connections/l_french_ridge_lap.py
compas_timber/connections/l_lap.py
compas_timber/connections/l_miter.py
compas_timber/connections/lap_joint.py
compas_timber/connections/oligina.py
compas_timber/connections/plate_butt_joint.py
compas_timber/connections/plate_joint.py
compas_timber/connections/plate_miter_joint.py
compas_timber/connections/solver.py
compas_timber/connections/t_birdsmouth.py
compas_timber/connections/t_butt.py
compas_timber/connections/t_dovetail.py
compas_timber/connections/t_lap.py
compas_timber/connections/t_step_joint.py
compas_timber/connections/t_tenon_mortise.py
compas_timber/connections/utilities.py
compas_timber/connections/wall_joint.py
compas_timber/connections/x_lap.py
compas_timber/connections/x_notch.py
compas_timber/connections/y_butt.py
compas_timber/design/__init__.py
compas_timber/design/slab_populator.py
compas_timber/design/wall_details.py
compas_timber/design/wall_from_surface.py
compas_timber/design/wall_populator.py
compas_timber/design/workflow.py
compas_timber/elements/__init__.py
compas_timber/elements/beam.py
compas_timber/elements/fastener.py
compas_timber/elements/features.py
compas_timber/elements/plate.py
compas_timber/elements/slab.py
compas_timber/elements/timber.py
compas_timber/elements/wall.py
compas_timber/elements/fasteners/__init__.py
compas_timber/elements/fasteners/ball_node_fastener.py
compas_timber/elements/fasteners/plate_fastener.py
compas_timber/errors/__init__.py
compas_timber/fabrication/__init__.py
compas_timber/fabrication/btlx.py
compas_timber/fabrication/double_cut.py
compas_timber/fabrication/dovetail_mortise.py
compas_timber/fabrication/dovetail_tenon.py
compas_timber-1.0.4.dist-info/licenses/LICENSE
compas_timber-1.0.4.dist-info/METADATA
compas_timber-1.0.4.dist-info/WHEEL
compas_timber-1.0.4.dist-info/top_level.txt
compas_timber-1.0.4.dist-info/RECORD
