Metadata-Version: 2.4
Name: compas_timber
Version: 1.0.4
Summary: COMPAS package for modeling, designing and fabricating timber assemblies.
Author-email: Aleksandra Anna Apolinarska <apolinarska@arch.ethz.ch>, Chen Kasirer <kasirer@arch.ethz.ch>, Gonzalo Casas <casas@arch.ethz.ch>, Jonas Haldemann <haldemann@arch.ethz.ch>, Oliver Appling Bucklin <bucklin@arch.ethz.ch>, "Aurèle L. Gheyselinck" <gheyselinck@arch.ethz.ch>, Panayiotis Papacharalambous <papacharalambous@arch.ethz.ch>, Anastasiia Stryzhevska <astryzhevska@arch.ethz.ch>, Jelle Feringa <jelleferinga@gmail.com>, Joseph Kenny <jk6372@princeton.edu>, Beverly Lytle <lytle@arch.
License: MIT License
Project-URL: Homepage, https://gramaziokohler.github.io/compas_timber/latest/
Project-URL: Repository, https://github.com/gramaziokohler/compas_timber
Classifier: Development Status :: 4 - Beta
Classifier: Topic :: Scientific/Engineering
Classifier: Programming Language :: Python
Classifier: Programming Language :: Python :: 3
Classifier: Programming Language :: Python :: 3.9
Classifier: Programming Language :: Python :: 3.10
Classifier: Programming Language :: Python :: 3.11
Requires-Python: >=3.9
License-File: LICENSE
Requires-Dist: rtree
Requires-Dist: compas<3.0,>=2.0
Requires-Dist: compas_model==0.4.4
Provides-Extra: dev
Requires-Dist: attrs>=17.4; extra == "dev"
Requires-Dist: black>=22.12.0; extra == "dev"
Requires-Dist: bump-my-version; extra == "dev"
Requires-Dist: compas_invocations2; extra == "dev"
Requires-Dist: invoke>=0.14; extra == "dev"
Requires-Dist: ruff; extra == "dev"
Requires-Dist: sphinx_compas2_theme; extra == "dev"
Requires-Dist: sphinxcontrib-mermaid; extra == "dev"
Requires-Dist: twine; extra == "dev"
Requires-Dist: build; extra == "dev"
Requires-Dist: wheel; extra == "dev"
Requires-Dist: pytest-mock; extra == "dev"
Requires-Dist: build; extra == "dev"
Requires-Dist: pythonnet; extra == "dev"
Requires-Dist: tomlkit; extra == "dev"
Requires-Dist: pytest-cov; extra == "dev"
Dynamic: license-file
